{
  "symbol": "EMSTEEL",
  "narrator": "nemotron",
  "generated_at": "2026-06-19T02:03:28+00:00",
  "short_term": {
    "reasons": [
      "Positive price momentum and constructive disclosure tone",
      "Resilient balance sheet (Stability 69) offering near-term downside buffer",
      "Dividend score of 61 provides modest income support for holders",
      "Industrial franchise benefits from ongoing UAE infrastructure activity"
    ],
    "risks": [
      "A surprise filing or sector-wide move could shift the picture quickly",
      "Growth score of 47 limits near-term upside catalysts",
      "Trading materially above model fair value signals overvaluation risk",
      "Neutral stance with only medium conviction reflects balanced but uncertain setup"
    ],
    "what_would_change_view": "Sustained earnings improvement or a dividend uplift signaling management confidence"
  },
  "long_term": {
    "reasons": [
      "Resilient balance sheet (Stability 69) underpins long-term staying power",
      "Dividend score of 61 offers structural income potential for patient holders",
      "Established UAE industrial franchise with strategic relevance",
      "Macro tailwinds from UAE industrialization and infrastructure pipeline"
    ],
    "risks": [
      "Execution and macro conditions remain the key swing factors",
      "Growth score of 47 suggests limited structural growth trajectory",
      "Significant overvaluation vs model fair value caps long-term upside",
      "Low conviction on long-term Neutral stance reflects high uncertainty"
    ],
    "what_would_change_view": "Clear execution on a credible growth strategy or material improvement in macro conditions"
  },
  "valuation_note": "The market likely prices in EMSTEEL's strategic role in UAE industrialization and infrastructure spending that the model does not fully capture; the gap could close if earnings delivery disappoints or macro headwinds intensify"
}