{
  "symbol": "JULPHAR",
  "narrator": "freeagent",
  "generated_at": "2026-06-24T16:13:15+00:00",
  "short_term": {
    "reasons": [
      "Recent disclosure tone skews positive",
      "Stability score near the midpoint provides a defensive floor in a defensive sector",
      "Dividend score in the low-60s offers some income anchor for holders",
      "Absence of an immediate negative catalyst keeps near-term pressure limited"
    ],
    "risks": [
      "A surprise filing or a sector-wide move could shift the picture quickly",
      "Positive disclosure tone may not translate into sustained price momentum without volume follow-through",
      "Any adverse regulatory headline in the broader healthcare space could unwind near-term sentiment",
      "Liquidity on ADX can amplify moves, making the stock vulnerable to sudden drawdowns"
    ],
    "what_would_change_view": "A material new contract, regulatory approval, or a sharper improvement in disclosure tone would demand a re-rate."
  },
  "long_term": {
    "reasons": [
      "Mixed fundamentals; no single pillar stands out",
      "Stability score suggests moderate operational consistency but not enough to offset growth constraints",
      "Dividend score indicates a modest income profile that may attract long-term holders",
      "Healthcare sector exposure offers relative defensiveness in periods of macro stress"
    ],
    "risks": [
      "Weak growth signal (Growth 39/100)",
      "Growth score well below 50 points to limited organic expansion and reliance on one-off items or pricing power",
      "Dividend income could come under pressure if earnings stay stagnant",
      "Structural competition or pricing pressure could erode margins over time"
    ],
    "what_would_change_view": "Sustained improvement in the Growth score toward or above 50, backed by visible revenue expansion, would alter the long-term Neutral stance."
  },
  "valuation_note": "With neutral stances across both horizons and no single dominant signal, the valuation appears fairly embedded. Retail investors should not expect a dramatic re-rating unless a clear catalyst emerges or the growth trajectory shifts materially."
}